plai/__init__.py
plai/__main__.py
plai/environment.py
plai/interpreter.py
plai/symbol.py
plai/validation.py
plai/modules/__init__.py
plai/modules/columns.py
plai/modules/frame.py
plai/modules/py_importer.py
plai/parser/__init__.py
plai/parser/grammar.py
plai/parser/parser.py
plai/parser/transformer.py
tests/__init__.py
tests/conftest.py
tests/test_environment.py
tests/test_evaluation.py
tests/test_grammar.py
tests/test_modules.py
tests/test_validation.py
plai-0.1.dist-info/LICENSE
plai-0.1.dist-info/METADATA
plai-0.1.dist-info/WHEEL
plai-0.1.dist-info/top_level.txt
plai-0.1.dist-info/RECORD
