Metadata-Version: 2.1
Name: plai
Version: 0.1
Summary: Programming language to create data manipulation pipelines.
Home-page: https://github.com/matheusbsilva/plai
License: MIT
Platform: UNKNOWN
Classifier: Programming Language :: Python :: 3
Classifier: License :: OSI Approved :: MIT License
Classifier: Operating System :: OS Independent
Requires-Python: >=3.6
License-File: LICENSE
Requires-Dist: lark-parser (>=0.7.8)
Requires-Dist: pandas (>=1.1.5)
